flerken/__init__.py
flerken/_version.py
flerken/audio/__init__.py
flerken/audio/transforms.py
flerken/datasets/__init__.py
flerken/datasets/audiovisual_dali_pipes.py
flerken/datasets/audiovisual_dataset.py
flerken/datasets/bss_dataset.py
flerken/datasets/dataset_tools.py
flerken/datasets/inpainting_dataset.py
flerken/datasets/pytorch_pipes.py
flerken/datasets/hmdb51/__init__.py
flerken/datasets/hmdb51/hmdb51.py
flerken/datasets/hmdb51/hmdb51_json.py
flerken/datasets/hmdb51/n_frames_ucf101_hmdb51.py
flerken/datasets/hmdb51/spatial_transforms.py
flerken/datasets/hmdb51/target_transforms.py
flerken/datasets/hmdb51/temporal_transforms.py
flerken/datasets/hmdb51/video_jpg_ucf101_hmdb51.py
flerken/datasets/voxceleb/__init__.py
flerken/framework/__init__.py
flerken/framework/allocator.py
flerken/framework/classitems.py
flerken/framework/debug.py
flerken/framework/experiment.py
flerken/framework/framework.py
flerken/framework/meters.py
flerken/framework/model.py
flerken/framework/network_initialization.py
flerken/framework/python_inheritance.py
flerken/framework/sqlite_tools.py
flerken/framework/traceback_gradients.py
flerken/framework/utils.py
flerken/models/MixtedConvolutions.py
flerken/models/R2Plus1D.py
flerken/models/ResNet3D.py
flerken/models/UNet.py
flerken/models/UNetV2.py
flerken/models/UNetV3.py
flerken/models/VGG.py
flerken/models/__init__.py
flerken/models/film.py
flerken/models/sop_unet.py
flerken/transforms/__init__.py
flerken/transforms/numpy_transforms.py
flerken/transforms/transforms.py
flerken/utils/__init__.py
flerken/utils/losses.py
flerken/utils/plots.py
flerken/video/__init__.py
flerken/video/io.py
flerken/video/readers.py
flerken/video/utils.py
test/__init__.py
test/audio/__init__.py
test/audio/test_functionals.py
test/framework/__init__.py
test/framework/test_allocator.py
test/framework/test_classitems.py
test/framework/test_experiment.py
test/framework/test_framework.py
test/framework/test_model.py
test/framework/test_python_inheritance.py
flerken_nightly-1.7.post5.dist-info/METADATA
flerken_nightly-1.7.post5.dist-info/WHEEL
flerken_nightly-1.7.post5.dist-info/top_level.txt
flerken_nightly-1.7.post5.dist-info/RECORD
