Metadata-Version: 2.1
Name: flerken-nightly
Version: 1.7.post5
Summary: PyTorch extension with simplified trainer. 
Home-page: https://github.com/JuanFMontesinos/flerken
Author: Juan Montesinos
Author-email: juanfelipe.montesinos@upf.edu
License: UNKNOWN
Platform: UNKNOWN
Classifier: Programming Language :: Python :: 3
Requires-Dist: tqdm
Requires-Dist: numpy
Requires-Dist: sklearn
